ARCHI/multiplexer/mux2_1.vhd
----------------------------
-- Multiplexeur 2 vers 1
----------------------------


library ieee;
use ieee.std_logic_1164.all;

-- entitee multiplexeur 2 vers 1
entity mux2_1 is
  port (
    input_signals : in std_logic_vector(1 downto 0);
    select_signal : in std_logic;
    output_signal : out std_logic
  );
end mux2_1;

-- architecture "data flow"
architecture mux2_1_df of mux2_1 is
begin
  with select_signal select
    output_signal <=
      -- on selectionne l'entree 0
      input_signals(0) when '0',
      -- on selectionne l'entree 1
      input_signals(1) when '1',
      -- comportement non definis
      'X' when others;
end mux2_1_df;

ARCHI/multiplexer/mux4_1.vhd
----------------------------
-- Multiplexer 4 vers 1
----------------------------


library ieee;
use ieee.std_logic_1164.all;

-- entitee multiplexeur 4 vers 1
entity mux4_1 is
  port (
    input_signals : in std_logic_vector(3 downto 0);
    select_signal : in std_logic_vector(1 downto 0);
    output_signal : out std_logic
  );
end mux4_1;

-- architecture "data flow"
architecture mux4_1_df of mux4_1 is
  
  -- on utilise des multiplexexeurs 
  -- 2 vers 1 en composants internes.
  component mux2_1
  port (
    input_signals : in std_logic_vector(1 downto 0);
    select_signal : in std_logic;
    output_signal : out std_logic
  );
  end component;

  -- 2 sorties intermediaires
  -- pour 2 multiplexeurs 2 vers 1.
  signal output_mux2_1_A : std_logic;
  signal output_mux2_1_B : std_logic;

begin
  -- instance A de mux2_1
  mux2_1_A : mux2_1 port map (
    input_signals(0)  => input_signals(0),
    input_signals(1)  => input_signals(1),
    select_signal     => select_signal(0),
    output_signal     => output_mux2_1_A
  );

  -- instance B de mux2_1
  mux2_1_B : mux2_1 port map (
    input_signals(0)  => input_signals(2),
    input_signals(1)  => input_signals(3),
    select_signal     => select_signal(0),
    output_signal     => output_mux2_1_B
  );

  -- instance C de mux2_1
  mux2_1_C : mux2_1 port map (
    input_signals(0)  => output_mux2_1_A,
    input_signals(1)  => output_mux2_1_B,
    select_signal     => select_signal(1),
    output_signal     => output_signal
  );
end mux4_1_df;

ARCHI/multiplexer/test_mux4_1.vhd
----------------------------
-- Test Multiplexeur 2 vers 1
----------------------------


library ieee;
use ieee.std_logic_1164.all;

-- entitee de test pour mux2_1
entity test_mux4_1 is
end test_mux4_1;

-- architecture pour le test
architecture test_mux4_1_arc of test_mux4_1 is
  -- signaux a afficher au debug
  signal input_signals  : std_logic_vector(3 downto 0);
  signal select_signal  : std_logic_vector(1 downto 0);
  signal output_signal  : std_logic;

  -- composant a tester
  component mux4_1
  port (
    input_signals : in std_logic_vector(3 downto 0);
    select_signal : in std_logic_vector(1 downto 0);
    output_signal : out std_logic
  );
  end component;
begin
  -- instance du composant a tester
  mux4_1_inst : mux4_1 port map (
    -- l'interface est la meme que 
    -- celle de l'arhictecture de test !
    -- On connecte donc 1 pour 1.
    input_signals,
    select_signal,
    output_signal
  );

  -- processus de test
  process
    type table_verite is array (0 to 15) of std_logic_vector(3 downto 0);
    type table_selection is array (0 to 3) of std_logic_vector(1 downto 0);
    -- entrees possibles
    constant tdv : table_verite := 
      ( "0000", "0001", "0010", "0011",
        "0100", "0101", "0110", "0111",
        "1000", "1001", "1010", "1011",
        "1100", "1101", "1110", "1111");
    -- selections possibles
    constant tds : table_selection :=
      ("00", "01", "10", "11");
  begin
    -- test de toutes les combinaisons
    for i in tds'range loop
      for j in tdv'range loop
        select_signal <= tds(i);
        input_signals <= tdv(j);
        wait for 5 ns;
      end loop;
    end loop;
    
    wait;
  end process;

end test_mux4_1_arc;

ARCHI/multiplexer/test_mux4_1.vcd
$date
  Mon Sep 23 22:52:01 2019
$end
$version
  GHDL v0
$end
$timescale
  1 fs
$end
$scope module standard $end
$upscope $end
$scope module std_logic_1164 $end
$upscope $end
$scope module test_mux4_1 $end
$var reg 4 ! input_signals[3:0] $end
$var reg 2 " select_signal[1:0] $end
$var reg 1 # output_signal $end
$scope module mux4_1_inst $end
$var reg 4 $ input_signals[3:0] $end
$var reg 2 % select_signal[1:0] $end
$var reg 1 & output_signal $end
$var reg 1 ' output_mux2_1_a $end
$var reg 1 ( output_mux2_1_b $end
$scope module mux2_1_a $end
$var reg 2 ) input_signals[1:0] $end
$var reg 1 * select_signal $end
$var reg 1 + output_signal $end
$upscope $end
$scope module mux2_1_b $end
$var reg 2 , input_signals[1:0] $end
$var reg 1 - select_signal $end
$var reg 1 . output_signal $end
$upscope $end
$scope module mux2_1_c $end
$var reg 2 / input_signals[1:0] $end
$var reg 1 0 select_signal $end
$var reg 1 1 output_signal $end
$upscope $end
$upscope $end
$upscope $end
$enddefinitions $end
#0
b0000 !
b00 "
0#
b0000 $
b00 %
0&
0'
0(
b00 )
0*
0+
b00 ,
0-
0.
b00 /
00
01
#5000000
b0001 !
1#
b0001 $
1&
1'
b01 )
1+
b01 /
11
#10000000
b0010 !
0#
b0010 $
0&
0'
b10 )
0+
b00 /
01
#15000000
b0011 !
1#
b0011 $
1&
1'
b11 )
1+
b01 /
11
#20000000
b0100 !
0#
b0100 $
0&
0'
1(
b00 )
0+
b01 ,
1.
b10 /
01
#25000000
b0101 !
1#
b0101 $
1&
1'
b01 )
1+
b11 /
11
#30000000
b0110 !
0#
b0110 $
0&
0'
b10 )
0+
b10 /
01
#35000000
b0111 !
1#
b0111 $
1&
1'
b11 )
1+
b11 /
11
#40000000
b1000 !
0#
b1000 $
0&
0'
0(
b00 )
0+
b10 ,
0.
b00 /
01
#45000000
b1001 !
1#
b1001 $
1&
1'
b01 )
1+
b01 /
11
#50000000
b1010 !
0#
b1010 $
0&
0'
b10 )
0+
b00 /
01
#55000000
b1011 !
1#
b1011 $
1&
1'
b11 )
1+
b01 /
11
#60000000
b1100 !
0#
b1100 $
0&
0'
1(
b00 )
0+
b11 ,
1.
b10 /
01
#65000000
b1101 !
1#
b1101 $
1&
1'
b01 )
1+
b11 /
11
#70000000
b1110 !
0#
b1110 $
0&
0'
b10 )
0+
b10 /
01
#75000000
b1111 !
1#
b1111 $
1&
1'
b11 )
1+
b11 /
11
#80000000
b0000 !
b01 "
0#
b0000 $
b01 %
0&
0'
0(
b00 )
1*
0+
b00 ,
1-
0.
b00 /
01
#85000000
b0001 !
b0001 $
b01 )
#90000000
b0010 !
1#
b0010 $
1&
1'
b10 )
1+
b01 /
11
#95000000
b0011 !
b0011 $
b11 )
#100000000
b0100 !
0#
b0100 $
0&
0'
b00 )
0+
b01 ,
b00 /
01
#105000000
b0101 !
b0101 $
b01 )
#110000000
b0110 !
1#
b0110 $
1&
1'
b10 )
1+
b01 /
11
#115000000
b0111 !
b0111 $
b11 )
#120000000
b1000 !
0#
b1000 $
0&
0'
1(
b00 )
0+
b10 ,
1.
b10 /
01
#125000000
b1001 !
b1001 $
b01 )
#130000000
b1010 !
1#
b1010 $
1&
1'
b10 )
1+
b11 /
11
#135000000
b1011 !
b1011 $
b11 )
#140000000
b1100 !
0#
b1100 $
0&
0'
b00 )
0+
b11 ,
b10 /
01
#145000000
b1101 !
b1101 $
b01 )
#150000000
b1110 !
1#
b1110 $
1&
1'
b10 )
1+
b11 /
11
#155000000
b1111 !
b1111 $
b11 )
#160000000
b0000 !
b10 "
0#
b0000 $
b10 %
0&
0'
0(
b00 )
0*
0+
b00 ,
0-
0.
b00 /
10
01
#165000000
b0001 !
b0001 $
1'
b01 )
1+
b01 /
#170000000
b0010 !
b0010 $
0'
b10 )
0+
b00 /
#175000000
b0011 !
b0011 $
1'
b11 )
1+
b01 /
#180000000
b0100 !
1#
b0100 $
1&
0'
1(
b00 )
0+
b01 ,
1.
b10 /
11
#185000000
b0101 !
b0101 $
1'
b01 )
1+
b11 /
#190000000
b0110 !
b0110 $
0'
b10 )
0+
b10 /
#195000000
b0111 !
b0111 $
1'
b11 )
1+
b11 /
#200000000
b1000 !
0#
b1000 $
0&
0'
0(
b00 )
0+
b10 ,
0.
b00 /
01
#205000000
b1001 !
b1001 $
1'
b01 )
1+
b01 /
#210000000
b1010 !
b1010 $
0'
b10 )
0+
b00 /
#215000000
b1011 !
b1011 $
1'
b11 )
1+
b01 /
#220000000
b1100 !
1#
b1100 $
1&
0'
1(
b00 )
0+
b11 ,
1.
b10 /
11
#225000000
b1101 !
b1101 $
1'
b01 )
1+
b11 /
#230000000
b1110 !
b1110 $
0'
b10 )
0+
b10 /
#235000000
b1111 !
b1111 $
1'
b11 )
1+
b11 /
#240000000
b0000 !
b11 "
0#
b0000 $
b11 %
0&
0'
0(
b00 )
1*
0+
b00 ,
1-
0.
b00 /
01
#245000000
b0001 !
b0001 $
b01 )
#250000000
b0010 !
b0010 $
1'
b10 )
1+
b01 /
#255000000
b0011 !
b0011 $
b11 )
#260000000
b0100 !
b0100 $
0'
b00 )
0+
b01 ,
b00 /
#265000000
b0101 !
b0101 $
b01 )
#270000000
b0110 !
b0110 $
1'
b10 )
1+
b01 /
#275000000
b0111 !
b0111 $
b11 )
#280000000
b1000 !
1#
b1000 $
1&
0'
1(
b00 )
0+
b10 ,
1.
b10 /
11
#285000000
b1001 !
b1001 $
b01 )
#290000000
b1010 !
b1010 $
1'
b10 )
1+
b11 /
#295000000
b1011 !
b1011 $
b11 )
#300000000
b1100 !
b1100 $
0'
b00 )
0+
b11 ,
b10 /
#305000000
b1101 !
b1101 $
b01 )
#310000000
b1110 !
b1110 $
1'
b10 )
1+
b11 /
#315000000
b1111 !
b1111 $
b11 )
