ARCHI/multiplexer/mux2_1.vhd
----------------------------
-- Multiplexeur 2 vers 1
----------------------------


library ieee;
use ieee.std_logic_1164.all;

-- entitee multiplexeur 2 vers 1
entity mux2_1 is
  port (
    input_signals : in std_logic_vector(1 downto 0);
    select_signal : in std_logic;
    output_signal : out std_logic
  );
end mux2_1;

-- architecture "data flow"
architecture mux2_1_df of mux2_1 is
begin
  with select_signal select
    output_signal <=
      -- on selectionne l'entree 0
      input_signals(0) when '0',
      -- on selectionne l'entree 1
      input_signals(1) when '1',
      -- comportement non definis
      'X' when others;
end mux2_1_df;

ARCHI/multiplexer/test_mux2_1.vhd
----------------------------
-- Test Multiplexeur 2 vers 1
----------------------------


library ieee;
use ieee.std_logic_1164.all;

-- entitee de test pour mux2_1
entity test_mux2_1 is
end test_mux2_1;

-- architecture pour le test
architecture test_mux2_1_arc of test_mux2_1 is
  -- signaux a afficher au debug
  signal input_signals : std_logic_vector(1 downto 0);
  signal select_signal : std_logic;
  signal output_signal : std_logic;

  -- composant a tester
  component mux2_1
  port (
    input_signals : in std_logic_vector(1 downto 0);
    select_signal : in std_logic;
    output_signal : out std_logic
  );
  end component;
begin
  -- instance du composant a tester
  mux2_1_inst : mux2_1 port map (
    -- l'interface est la meme que 
    -- celle de l'arhictecture de test !
    -- On connecte donc 1 pour 1.
    input_signals,
    select_signal,
    output_signal
  );

  -- processus de test
  process
    type table_verite is array (0 to 3) of std_logic_vector(1 downto 0);
    constant tdv : table_verite := ("00", "01", "10", "11");
  begin
    -- table pour selection
    -- du signal 0
    select_signal <= '0';
    for i in tdv'range loop
      input_signals <= tdv(i);
      wait for 5 ns;
    end loop;

    -- table pour selection
    -- du signal 1
    select_signal <= '1';
    for i in tdv'range loop
      input_signals <= tdv(i);
      wait for 5 ns;
    end loop;
    
    wait;
  end process;

end test_mux2_1_arc;

ARCHI/multiplexer/test_mux2_1.vcd
$date
  Mon Sep 23 22:48:55 2019
$end
$version
  GHDL v0
$end
$timescale
  1 fs
$end
$scope module standard $end
$upscope $end
$scope module std_logic_1164 $end
$upscope $end
$scope module test_mux2_1 $end
$var reg 2 ! input_signals[1:0] $end
$var reg 1 " select_signal $end
$var reg 1 # output_signal $end
$scope module mux2_1_inst $end
$var reg 2 $ input_signals[1:0] $end
$var reg 1 % select_signal $end
$var reg 1 & output_signal $end
$upscope $end
$upscope $end
$enddefinitions $end
#0
b00 !
0"
0#
b00 $
0%
0&
#5000000
b01 !
1#
b01 $
1&
#10000000
b10 !
0#
b10 $
0&
#15000000
b11 !
1#
b11 $
1&
#20000000
b00 !
1"
0#
b00 $
1%
0&
#25000000
b01 !
b01 $
#30000000
b10 !
1#
b10 $
1&
#35000000
b11 !
b11 $
